{
  "title": "Borderlands",
  "original_developer": "Gearbox Software",
  "original_publisher": "2K Games",
  "original_release_year": "2009",
  "releases": [
    {
      "platform": "ps3",
      "release_date": "2009",
      "regions": [
        {
          "region": "latam",
          "versions": [
            {
              "version": "Favoritos",
              "description": "O jogo possui manual e uma arte no verso do encarte. (Visto no Mercado Libre da Argentina e México)",
              "photos": [
                {
                  "url": "../static/assets/img/games/ps3/favoritos/latam/borderlands.jpg",
                  "caption": "...",
                  "author": "Mercado Libre"
                },
                {
                  "url": "../static/assets/img/games/ps3/favoritos/latam/borderlands_inside.jpg",
                  "caption": "...",
                  "author": "Mercado Libre"
                }
              ]
            }
          ]
        }
      ]
    },
    {
      "platform": "xbox-360",
      "release_date": "2009"
    },
    {
      "platform": "windows",
      "release_date": "2009"
    },
    {
      "platform": "osx",
      "release_date": "2010"
    },
    {
      "platform": "ps4",
      "release_date": "2019",
      "description": "Versão remasterizada"
    },
    {
      "platform": "xbox-one",
      "release_date": "2019",
      "description": "Versão remasterizada"
    },
    {
      "platform": "switch",
      "release_date": "2020",
      "description": "Versão remasterizada"
    }
  ],
  "pingbacks": [
    {
      "title": "Lista completa da coleção Favoritos do PlayStation 3",
      "url": "/lista-jogos-ps3-serie-favoritos"
    }
  ]
}
