{
  "title": "Killzone 3",
  "original_developer": "Guerrilla Games",
  "original_publisher": "Sony Computer Entertainment",
  "original_release_year": "2011",
  "releases": [
    {
      "platform": "ps3",
      "regions": [
        {
          "region": "latam",
          "versions": [
            {
              "version": "Favoritos",
              "description": "(com manual) Argentina, Chile, México, Perú",
              "photos": [
                {
                  "url": "../static/assets/img/games/ps3/favoritos/latam/killzone-3.jpg",
                  "caption": "..."
                },
                {
                  "url": "../static/assets/img/games/ps3/favoritos/latam/killzone-3_inside.jpg",
                  "caption": "..."
                }
              ]
            }
          ]
        },
        {
          "region": "br",
          "versions": [
            {
              "version": "Favoritos",
              "region": "br",
              "photos": [
                {
                  "url": "../static/assets/img/games/ps3/favoritos/br/killzone-3.jpg",
                  "caption": "...",
                  "author": "PS3 Hunter",
                  "author-link": "https://www.instagram.com/ps3_hunter/"
                },
                {
                  "url": "../static/assets/img/games/ps3/favoritos/br/killzone-3_back.jpg",
                  "caption": "...",
                  "author": "PS3 Hunter",
                  "author-link": "https://www.instagram.com/ps3_hunter/"
                },
                {
                  "url": "../static/assets/img/games/ps3/favoritos/br/killzone-3_inside.jpg",
                  "caption": "...",
                  "author": "PS3 Hunter",
                  "author-link": "https://www.instagram.com/ps3_hunter/"
                }
              ]
            }
          ]
        }
      ]
    }
  ],
  "pingbacks": [
    {
      "title": "Lista completa da coleção Favoritos do PlayStation 3",
      "url": "/lista-jogos-ps3-serie-favoritos"
    }
  ]
}
